keggx/KEGG_compound_ids.txt
keggx/__init__.py
keggx/draw.py
keggx/keggx.py
keggx-0.1.2.dist-info/METADATA
keggx-0.1.2.dist-info/RECORD
keggx-0.1.2.dist-info/WHEEL
keggx-0.1.2.dist-info/top_level.txt
