Metadata-Version: 2.1
Name: keggx
Version: 0.1.2
Summary: Python package for manipulation and visualization of KEGG pathways.
Home-page: https://github.com/iamjli/keggx
Author: iamjli
Author-email: iamjli@mit.edu
License: MIT
Platform: UNKNOWN
Classifier: Programming Language :: Python :: 3.5
Classifier: Programming Language :: Python :: 3.6
Classifier: Programming Language :: Python :: 3.7
Requires-Python: >=3.5
Requires-Dist: pandas (>=0.20.1)
Requires-Dist: numpy (>=1.12.0)
Requires-Dist: networkx (>=2.0)
Requires-Dist: matplotlib
Requires-Dist: seaborn
Requires-Dist: requests
